langfabric/__init__.py
langfabric/fabric.py
langfabric/loader.py
langfabric/manager.py
langfabric/rebuild_models.py
langfabric/schema.py
langfabric-0.1.8.dist-info/LICENSE
langfabric-0.1.8.dist-info/METADATA
langfabric-0.1.8.dist-info/WHEEL
langfabric-0.1.8.dist-info/RECORD
