Metadata-Version: 2.3
Name: langfabric
Version: 0.1.8
Summary: Flexible LLM model initialization from YAML configuration.
License: MIT
Author: Phragman
Author-email: a@staphi.com
Requires-Python: >=3.9,<4.0
Classifier: License :: OSI Approved :: MIT License
Classifier: Programming Language :: Python :: 3
Classifier: Programming Language :: Python :: 3.9
Classifier: Programming Language :: Python :: 3.10
Classifier: Programming Language :: Python :: 3.11
Classifier: Programming Language :: Python :: 3.12
Classifier: Programming Language :: Python :: 3.13
Requires-Dist: langchain (>=0.3.26,<1.0)
Requires-Dist: langchain-community (>=0.3.26,<1.0)
Requires-Dist: langchain-groq (>=0.3.2,<1.0)
Requires-Dist: langchain-ollama (>=0.3.3,<0.4.0)
Requires-Dist: langchain-openai (>=0.3.24,<1.0)
Requires-Dist: pydantic (>=2.5,<3.0)
Requires-Dist: pyyaml (>=6.0,<7.0)
Requires-Dist: seyaml (>=0.1.1,<1.0)
